schemantis/__init__.py
schemantis/api_client.py
schemantis/api_response.py
schemantis/configuration.py
schemantis/exceptions.py
schemantis/rest.py
schemantis/api/__init__.py
schemantis/api/default_api.py
schemantis/models/__init__.py
schemantis/models/edge.py
schemantis/models/model_schema.py
schemantis/models/node.py
schemantis/models/retrieve_map_get200_response.py
schemantis/models/retrieve_map_get200_response_intermediate.py
schemantis/models/retrieve_map_get200_response_intermediate_edges_inner.py
schemantis/models/retrieve_map_get200_response_source.py
schemantis/models/retrieve_map_post_request.py
schemantis/models/retrieve_map_post_request_config.py
schemantis/models/update_schema_post200_response.py
schemantis/models/update_schema_post_request.py
schemantis-0.1.5.dist-info/METADATA
schemantis-0.1.5.dist-info/WHEEL
schemantis-0.1.5.dist-info/top_level.txt
schemantis-0.1.5.dist-info/RECORD
